<annotation verified="no">
  <folder>Saved_Pic_2</folder>
  <filename>1601251918.0886254</filename>
  <path>D:\project\bottle\09_28\Saved_Pic_2\1601251918.0886254.jpg</path>
  <source>
    <database>Unknown</database>
  </source>
  <size>
    <width>1280</width>
    <height>720</height>
    <depth>3</depth>
  </size>
  <segmented>0</segmented>
  <object>
    <name>bottle</name>
    <pose>Unspecified</pose>
    <truncated>0</truncated>
    <Difficult>0</Difficult>
    <bndbox>
      <xmin>449</xmin>
      <ymin>143</ymin>
      <xmax>486</xmax>
      <ymax>167</ymax>
    </bndbox>
  </object>
  <object>
    <name>bottle</name>
    <pose>Unspecified</pose>
    <truncated>1</truncated>
    <Difficult>0</Difficult>
    <bndbox>
      <xmin>1202</xmin>
      <ymin>347</ymin>
      <xmax>1280</xmax>
      <ymax>401</ymax>
    </bndbox>
  </object>
</annotation>
