<annotation>
    <folder>myPerson</folder>
    <filename>1675956590.jpg</filename>
    <size>
        <width>1280</width>
        <height>640</height>
        <depth>3</depth>
    </size>
    <object>
        <name>bottle</name>
        <pose>Unspecified</pose>
        <truncated>0</truncated>
        <difficult>0</difficult>
        <bndbox>
            <xmin>524</xmin>
            <ymin>374</ymin>
            <xmax>576</xmax>
            <ymax>439</ymax>
        </bndbox>
    </object>
    <object>
        <name>bottle</name>
        <pose>Unspecified</pose>
        <truncated>0</truncated>
        <difficult>0</difficult>
        <bndbox>
            <xmin>744</xmin>
            <ymin>296</ymin>
            <xmax>770</xmax>
            <ymax>322</ymax>
        </bndbox>
    </object>
</annotation>